parallelplot/__init__.py
parallelplot/cmaps.py
parallelplot/plot.py
parallelplot-0.6.5.dist-info/licenses/LICENSE
parallelplot-0.6.5.dist-info/METADATA
parallelplot-0.6.5.dist-info/WHEEL
parallelplot-0.6.5.dist-info/top_level.txt
parallelplot-0.6.5.dist-info/RECORD
