Metadata-Version: 2.4
Name: parallelplot
Version: 0.6.5
Summary: Plotting smooth parallel plots
Author-email: Tommy Markstein <parallelplot@markste.in>
License: MIT License
Project-URL: Homepage, https://github.com/markste-in/parallelplot
Keywords: parallel,plot,parallel-plot,smooth,parallelplot,matplotlib,plots
Classifier: License :: OSI Approved :: MIT License
Classifier: Programming Language :: Python
Classifier: Programming Language :: Python :: 3
Requires-Python: >=3.9
License-File: LICENSE
Requires-Dist: pandas
Requires-Dist: matplotlib
Provides-Extra: dev
Requires-Dist: build; extra == "dev"
Requires-Dist: twine; extra == "dev"
Dynamic: license-file
